velesdb/__init__.py
velesdb/__init__.pyi
velesdb/__pycache__/__init__.cpython-310.pyc
velesdb/velesdb.cp310-win_amd64.pyd
velesdb/velesdb.cpython-311-x86_64-linux-gnu.so
velesdb-1.1.0.dist-info/METADATA
velesdb-1.1.0.dist-info/WHEEL
velesdb-1.1.0.dist-info/licenses/LICENSE
velesdb-1.1.0.dist-info/RECORD
