Metadata-Version: 2.4
Name: velesdb
Version: 1.1.0
Classifier: Development Status :: 4 - Beta
Classifier: Intended Audience :: Developers
Classifier: Intended Audience :: Science/Research
Classifier: License :: Other/Proprietary License
Classifier: Operating System :: OS Independent
Classifier: Programming Language :: Python :: 3
Classifier: Programming Language :: Python :: 3.9
Classifier: Programming Language :: Python :: 3.10
Classifier: Programming Language :: Python :: 3.11
Classifier: Programming Language :: Python :: 3.12
Classifier: Programming Language :: Rust
Classifier: Topic :: Database
Classifier: Topic :: Scientific/Engineering :: Artificial Intelligence
Requires-Dist: pytest>=7.0 ; extra == 'dev'
Requires-Dist: numpy>=1.20 ; extra == 'dev'
Requires-Dist: maturin>=1.4 ; extra == 'dev'
Requires-Dist: numpy>=1.20 ; extra == 'numpy'
Provides-Extra: dev
Provides-Extra: numpy
License-File: LICENSE
Summary: A high-performance vector database for AI applications
Keywords: vector-database,embeddings,similarity-search,ai,machine-learning
Home-Page: https://velesdb.com
Author-email: VelesDB Team <contact@wiscale.fr>
License: Elastic License 2.0 (ELv2)
Requires-Python: >=3.9
Project-URL: Documentation, https://github.com/cyberlife-coder/VelesDB#readme
Project-URL: Homepage, https://github.com/cyberlife-coder/VelesDB
Project-URL: Issues, https://github.com/cyberlife-coder/VelesDB/issues
Project-URL: Repository, https://github.com/cyberlife-coder/VelesDB
